[
    {
        "year": 8,
        "price": 13000,
        "oddmeter": 99000,
        "fueltype": "Газ/Бензин",
        "engine_V": 2.49,
        "transmission": 2
    },
    {
        "year": 3,
        "price": 24500,
        "oddmeter": 68000,
        "engine_V": 2.49,
        "fueltype": "Бензин",
        "transmission": 2
    },
    {
        "year": 11,
        "price": 16000,
        "oddmeter": 243000,
        "fueltype": "Газ/Бензин",
        "engine_V": 3.5,
        "transmission": 2
    },
    {
        "year": 5,
        "price": 28500,
        "oddmeter": 19000,
        "engine_V": 2.5,
        "fueltype": "Бензин",
        "transmission": 2
    },
    {
        "year": 4,
        "price": 25400,
        "oddmeter": 88000,
        "engine_V": 2.49,
        "fueltype": "Бензин",
        "transmission": 2
    },
    {
        "year": 2,
        "price": 29235,
        "oddmeter": 50000,
        "engine_V": 2.5,
        "fueltype": "Бензин",
        "transmission": 2
    },
    {
        "year": 8,
        "price": 20800,
        "oddmeter": 66000,
        "engine_V": 2.49,
        "fueltype": "Бензин",
        "transmission": 2
    },
    {
        "year": 2,
        "price": 29700,
        "oddmeter": 32000,
        "engine_V": 2.49,
        "fueltype": "Бензин",
        "transmission": 2
    },
    {
        "year": 10,
        "price": 16500,
        "oddmeter": 155000,
        "engine_V": 2.5,
        "fueltype": "Бензин",
        "transmission": 2
    },
    {
        "year": 19,
        "price": 6900,
        "oddmeter": 252000,
        "engine_V": 3.0,
        "fueltype": "Бензин",
        "transmission": 2
    },
    {
        "year": 6,
        "price": 16800,
        "oddmeter": 124000,
        "fueltype": "Газ/Бензин",
        "engine_V": 2.49,
        "transmission": 2
    },
    {
        "year": 2,
        "price": 38500,
        "oddmeter": 11000,
        "engine_V": 2.5,
        "fueltype": "Бензин",
        "transmission": 2
    },
    {
        "year": 6,
        "price": 22300,
        "oddmeter": 95000,
        "engine_V": 2.5,
        "fueltype": "Бензин",
        "transmission": 2
    },
    {
        "year": 15,
        "price": 9000,
        "oddmeter": 246000,
        "fueltype": "Газ/Бензин",
        "engine_V": 2.4,
        "transmission": 2
    },
    {
        "year": 16,
        "price": 8888,
        "oddmeter": 167000,
        "engine_V": 2.4,
        "fueltype": "Бензин",
        "transmission": 2
    },
    {
        "year": 7,
        "price": 17850,
        "oddmeter": 165000,
        "engine_V": 2.5,
        "fueltype": "Гібрид",
        "transmission": 2
    },
    {
        "year": 9,
        "price": 12990,
        "oddmeter": 150000,
        "engine_V": 2.5,
        "fueltype": "Бензин",
        "transmission": 2
    },
    {
        "year": 0,
        "price": 40786,
        "oddmeter": 0,
        "engine_V": 2.5,
        "fueltype": "Гібрид",
        "transmission": 4
    },
    {
        "year": 19,
        "price": 3300,
        "oddmeter": 320000,
        "engine_V": 2.4,
        "fueltype": "Бензин",
        "transmission": 1
    },
    {
        "year": 15,
        "price": 9300,
        "oddmeter": 163000,
        "fueltype": "Газ/Бензин",
        "engine_V": 2.36,
        "transmission": 2
    },
    {
        "year": 11,
        "price": 14800,
        "oddmeter": 174000,
        "fueltype": "Газ/Бензин",
        "engine_V": 2.5,
        "transmission": 2
    },
    {
        "year": 12,
        "price": 11000,
        "oddmeter": 210000,
        "engine_V": 2.5,
        "fueltype": "Бензин",
        "transmission": 2
    },
    {
        "year": 19,
        "price": 6900,
        "oddmeter": 208000,
        "fueltype": "Газ/Бензин",
        "engine_V": 2.4,
        "transmission": 2
    },
    {
        "year": 4,
        "price": 23499,
        "oddmeter": 82000,
        "engine_V": 2.49,
        "fueltype": "Бензин",
        "transmission": 2
    },
    {
        "year": 15,
        "price": 9500,
        "oddmeter": 240000,
        "fueltype": "Газ/Бензин",
        "engine_V": 2.4,
        "transmission": 2
    },
    {
        "year": 17,
        "price": 8300,
        "oddmeter": 204000,
        "engine_V": 3.46,
        "fueltype": "Бензин",
        "transmission": 3
    },
    {
        "year": 10,
        "price": 13000,
        "oddmeter": 238000,
        "fueltype": "Газ/Бензин",
        "engine_V": 2.5,
        "transmission": 2
    },
    {
        "year": 11,
        "price": 15500,
        "oddmeter": 127000,
        "engine_V": 2.5,
        "fueltype": "Бензин",
        "transmission": 2
    },
    {
        "year": 17,
        "price": 9700,
        "oddmeter": 305000,
        "fueltype": "Газ/Бензин",
        "engine_V": 3.5,
        "transmission": 2
    },
    {
        "year": 10,
        "price": 16500,
        "oddmeter": 175000,
        "fueltype": "Газ/Бензин",
        "engine_V": 2.5,
        "transmission": 2
    },
    {
        "year": 2,
        "price": 31000,
        "oddmeter": 17000,
        "engine_V": 2.49,
        "fueltype": "Бензин",
        "transmission": 2
    },
    {
        "year": 6,
        "price": 24999,
        "oddmeter": 121000,
        "engine_V": 2.5,
        "fueltype": "Бензин",
        "transmission": 2
    },
    {
        "year": 11,
        "price": 14800,
        "oddmeter": 177000,
        "fueltype": "Газ/Бензин",
        "engine_V": 2.5,
        "transmission": 2
    },
    {
        "year": 1,
        "price": 39999,
        "oddmeter": 13000,
        "engine_V": 2.5,
        "fueltype": "Гібрид",
        "transmission": 2
    },
    {
        "year": 13,
        "price": 12800,
        "oddmeter": 205000,
        "engine_V": 2.5,
        "fueltype": "Гібрид",
        "transmission": 2
    },
    {
        "year": 9,
        "price": 19000,
        "oddmeter": 56000,
        "engine_V": 2.49,
        "fueltype": "Бензин",
        "transmission": 2
    },
    {
        "year": 10,
        "price": 9850,
        "oddmeter": 170000,
        "engine_V": 2.5,
        "fueltype": "Бензин",
        "transmission": 2
    },
    {
        "year": 5,
        "price": 29300,
        "oddmeter": 84000,
        "engine_V": 2.49,
        "fueltype": "Бензин",
        "transmission": 2
    },
    {
        "year": 5,
        "price": 20900,
        "oddmeter": 226000,
        "engine_V": 2.49,
        "fueltype": "Бензин",
        "transmission": 2
    },
    {
        "year": 21,
        "price": 8000,
        "oddmeter": 450000,
        "fueltype": "Газ/Бензин",
        "engine_V": 3.0,
        "transmission": 2
    },
    {
        "year": 15,
        "price": 11000,
        "oddmeter": 190000,
        "fueltype": "Газ/Бензин",
        "engine_V": 3.5,
        "transmission": 2
    },
    {
        "year": 5,
        "price": 30500,
        "oddmeter": 69000,
        "engine_V": 2.49,
        "fueltype": "Бензин",
        "transmission": 2
    },
    {
        "year": 4,
        "price": 32640,
        "oddmeter": 82000,
        "engine_V": 2.5,
        "fueltype": "Гібрид",
        "transmission": 2
    },
    {
        "year": 0,
        "price": 34718,
        "oddmeter": 0,
        "engine_V": 2.5,
        "fueltype": "Бензин",
        "transmission": 2
    },
    {
        "year": 11,
        "price": 14800,
        "oddmeter": 216000,
        "fueltype": "Газ/Бензин",
        "engine_V": 2.5,
        "transmission": 2
    },
    {
        "year": 7,
        "price": 17900,
        "oddmeter": 104000,
        "fueltype": "Газ/Бензин",
        "engine_V": 2.49,
        "transmission": 2
    },
    {
        "year": 16,
        "price": 8800,
        "oddmeter": 262000,
        "engine_V": 3.5,
        "fueltype": "Бензин",
        "transmission": 2
    },
    {
        "year": 0,
        "price": 45700,
        "oddmeter": 17000,
        "engine_V": 2.49,
        "fueltype": "Гібрид",
        "transmission": 2
    },
    {
        "year": 7,
        "price": 14500,
        "oddmeter": 128000,
        "engine_V": 2.49,
        "fueltype": "Бензин",
        "transmission": 2
    },
    {
        "year": 17,
        "price": 10200,
        "oddmeter": 209000,
        "engine_V": 2.4,
        "fueltype": "Бензин",
        "transmission": 2
    },
    {
        "year": 5,
        "price": 27300,
        "oddmeter": 112000,
        "engine_V": 2.49,
        "fueltype": "Бензин",
        "transmission": 2
    },
    {
        "year": 4,
        "price": 37700,
        "oddmeter": 60000,
        "engine_V": 2.49,
        "fueltype": "Гібрид",
        "transmission": 3
    },
    {
        "year": 5,
        "price": 27900,
        "oddmeter": 89000,
        "engine_V": 2.49,
        "fueltype": "Бензин",
        "transmission": 2
    },
    {
        "year": 15,
        "price": 9400,
        "oddmeter": 198000,
        "fueltype": "Газ/Бензин",
        "engine_V": 2.4,
        "transmission": 2
    },
    {
        "year": 17,
        "price": 5800,
        "oddmeter": 318000,
        "fueltype": "Газ/Бензин",
        "engine_V": 2.4,
        "transmission": 2
    },
    {
        "year": 8,
        "price": 16500,
        "oddmeter": 199000,
        "fueltype": "Газ/Бензин",
        "engine_V": 2.49,
        "transmission": 2
    },
    {
        "year": 16,
        "price": 9500,
        "oddmeter": 216000,
        "engine_V": 2.4,
        "fueltype": "Бензин",
        "transmission": 2
    },
    {
        "year": 15,
        "price": 10300,
        "oddmeter": 196000,
        "fueltype": "Газ/Бензин",
        "engine_V": 3.46,
        "transmission": 2
    },
    {
        "year": 5,
        "price": 29000,
        "oddmeter": 66000,
        "engine_V": 2.5,
        "fueltype": "Бензин",
        "transmission": 2
    },
    {
        "year": 5,
        "price": 29500,
        "oddmeter": 86000,
        "fueltype": "Газ/Бензин",
        "engine_V": 2.49,
        "transmission": 2
    },
    {
        "year": 16,
        "price": 6500,
        "oddmeter": 200000,
        "fueltype": "Газ/Бензин",
        "engine_V": 2.4,
        "transmission": 2
    },
    {
        "year": 3,
        "price": 24500,
        "oddmeter": 17000,
        "engine_V": 2.5,
        "fueltype": "Бензин",
        "transmission": 2
    },
    {
        "year": 17,
        "price": 9300,
        "oddmeter": 294000,
        "fueltype": "Газ/Бензин",
        "engine_V": 3.5,
        "transmission": 2
    },
    {
        "year": 11,
        "price": 16500,
        "oddmeter": 187000,
        "fueltype": "Газ/Бензин",
        "engine_V": 2.5,
        "transmission": 2
    },
    {
        "year": 7,
        "price": 13900,
        "oddmeter": 187000,
        "engine_V": 2.49,
        "fueltype": "Бензин",
        "transmission": 3
    },
    {
        "year": 3,
        "price": 32300,
        "oddmeter": 100000,
        "engine_V": 2.5,
        "fueltype": "Гібрид",
        "transmission": 2
    },
    {
        "year": 4,
        "price": 21900,
        "oddmeter": 39000,
        "engine_V": 2.5,
        "fueltype": "Бензин",
        "transmission": 2
    },
    {
        "year": 8,
        "price": 21000,
        "oddmeter": 92000,
        "engine_V": 2.5,
        "fueltype": "Бензин",
        "transmission": 2
    },
    {
        "year": 17,
        "price": 9999,
        "oddmeter": 181000,
        "engine_V": 2.36,
        "fueltype": "Бензин",
        "transmission": 2
    },
    {
        "year": 6,
        "price": 22500,
        "oddmeter": 26000,
        "engine_V": 2.5,
        "fueltype": "Бензин",
        "transmission": 2
    },
    {
        "year": 15,
        "price": 11000,
        "oddmeter": 326000,
        "fueltype": "Газ/Бензин",
        "engine_V": 3.5,
        "transmission": 2
    },
    {
        "year": 2,
        "price": 28200,
        "oddmeter": 39000,
        "engine_V": 2.5,
        "fueltype": "Бензин",
        "transmission": 2
    },
    {
        "year": 6,
        "price": 23500,
        "oddmeter": 91000,
        "engine_V": 2.5,
        "fueltype": "Бензин",
        "transmission": 2
    },
    {
        "year": 6,
        "price": 24300,
        "oddmeter": 97000,
        "engine_V": 2.5,
        "fueltype": "Бензин",
        "transmission": 2
    },
    {
        "year": 17,
        "price": 9990,
        "oddmeter": 289000,
        "engine_V": 2.4,
        "fueltype": "Бензин",
        "transmission": 2
    },
    {
        "year": 15,
        "price": 8800,
        "oddmeter": 247000,
        "fueltype": "Газ/Бензин",
        "engine_V": 2.4,
        "transmission": 2
    },
    {
        "year": 17,
        "price": 9190,
        "oddmeter": 268000,
        "fueltype": "Газ/Бензин",
        "engine_V": 3.5,
        "transmission": 2
    },
    {
        "year": 12,
        "price": 18999,
        "oddmeter": 10000,
        "engine_V": 2.4,
        "fueltype": "Гібрид",
        "transmission": 2
    },
    {
        "year": 13,
        "price": 10200,
        "oddmeter": 162000,
        "fueltype": "Газ/Бензин",
        "engine_V": 2.4,
        "transmission": 2
    },
    {
        "year": 0,
        "price": 31680,
        "oddmeter": 0,
        "engine_V": 2.5,
        "fueltype": "Бензин",
        "transmission": 2
    },
    {
        "year": 0,
        "price": 40178,
        "oddmeter": 0,
        "engine_V": 2.5,
        "fueltype": "Гібрид",
        "transmission": 4
    },
    {
        "year": 6,
        "price": 23350,
        "oddmeter": 180000,
        "engine_V": 2.5,
        "fueltype": "Гібрид",
        "transmission": 2
    },
    {
        "year": 11,
        "price": 13500,
        "oddmeter": 150000,
        "engine_V": 2.5,
        "fueltype": "Бензин",
        "transmission": 2
    },
    {
        "year": 2,
        "price": 32500,
        "oddmeter": 1000,
        "engine_V": 2.49,
        "fueltype": "Бензин",
        "transmission": 2
    },
    {
        "year": 18,
        "price": 7100,
        "oddmeter": 220000,
        "fueltype": "Газ/Бензин",
        "engine_V": 3.0,
        "transmission": 2
    },
    {
        "year": 3,
        "price": 26700,
        "oddmeter": 38000,
        "engine_V": 2.49,
        "fueltype": "Гібрид",
        "transmission": 2
    },
    {
        "year": 16,
        "price": 10200,
        "oddmeter": 305000,
        "fueltype": "Газ/Бензин",
        "engine_V": 3.5,
        "transmission": 2
    },
    {
        "year": 11,
        "price": 12100,
        "oddmeter": 146000,
        "engine_V": 2.5,
        "fueltype": "Бензин",
        "transmission": 2
    },
    {
        "year": 15,
        "price": 13000,
        "oddmeter": 190000,
        "fueltype": "Газ/Бензин",
        "engine_V": 3.5,
        "transmission": 2
    },
    {
        "year": 6,
        "price": 23500,
        "oddmeter": 118000,
        "fueltype": "Газ/Бензин",
        "engine_V": 2.5,
        "transmission": 2
    },
    {
        "year": 0,
        "price": 37902,
        "oddmeter": 0,
        "engine_V": 2.5,
        "fueltype": "Гібрид",
        "transmission": 4
    },
    {
        "year": 0,
        "price": 37902,
        "oddmeter": 0,
        "engine_V": 2.5,
        "fueltype": "Гібрид",
        "transmission": 4
    },
    {
        "year": 15,
        "price": 8999,
        "oddmeter": 246000,
        "fueltype": "Газ/Бензин",
        "engine_V": 2.4,
        "transmission": 2
    },
    {
        "year": 0,
        "price": 34997,
        "oddmeter": 0,
        "engine_V": 2.5,
        "fueltype": "Бензин",
        "transmission": 2
    },
    {
        "year": 7,
        "price": 15999,
        "oddmeter": 160000,
        "fueltype": "Газ/Бензин",
        "engine_V": 2.5,
        "transmission": 2
    },
    {
        "year": 16,
        "price": 9500,
        "oddmeter": 198000,
        "fueltype": "Газ/Бензин",
        "engine_V": 3.5,
        "transmission": 2
    },
    {
        "year": 6,
        "price": 14900,
        "oddmeter": 120000,
        "fueltype": "Газ/Бензин",
        "engine_V": 2.49,
        "transmission": 2
    },
    {
        "year": 2,
        "price": 37000,
        "oddmeter": 43000,
        "engine_V": 2.49,
        "fueltype": "Гібрид",
        "transmission": 4
    },
    {
        "year": 15,
        "price": 8100,
        "oddmeter": 228000,
        "engine_V": 2.4,
        "fueltype": "Бензин",
        "transmission": 2
    },
    {
        "year": 8,
        "price": 16899,
        "oddmeter": 155000,
        "engine_V": 2.49,
        "fueltype": "Бензин",
        "transmission": 2
    },
    {
        "year": 26,
        "price": 4000,
        "oddmeter": 255000,
        "fueltype": "Газ/Бензин",
        "engine_V": 3.0,
        "transmission": 2
    },
    {
        "year": 12,
        "price": 11200,
        "oddmeter": 250000,
        "engine_V": 2.4,
        "fueltype": "Бензин",
        "transmission": 2
    },
    {
        "year": 2,
        "price": 28799,
        "oddmeter": 63000,
        "engine_V": 2.49,
        "fueltype": "Бензин",
        "transmission": 2
    },
    {
        "year": 20,
        "price": 5400,
        "oddmeter": 285000,
        "fueltype": "Газ/Бензин",
        "engine_V": 3.0,
        "transmission": 2
    },
    {
        "year": 3,
        "price": 24700,
        "oddmeter": 53000,
        "engine_V": 2.49,
        "fueltype": "Гібрид",
        "transmission": 2
    },
    {
        "year": 19,
        "price": 5999,
        "oddmeter": 294000,
        "engine_V": 3.0,
        "fueltype": "Бензин",
        "transmission": 2
    },
    {
        "year": 5,
        "price": 26999,
        "oddmeter": 80000,
        "fueltype": "Газ/Бензин",
        "engine_V": 2.49,
        "transmission": 2
    },
    {
        "year": 6,
        "price": 18500,
        "oddmeter": 89000,
        "engine_V": 2.49,
        "fueltype": "Бензин",
        "transmission": 2
    },
    {
        "year": 10,
        "price": 14500,
        "oddmeter": 225000,
        "engine_V": 2.5,
        "fueltype": "Гібрид",
        "transmission": 2
    },
    {
        "year": 5,
        "price": 24500,
        "oddmeter": 86000,
        "engine_V": 2.5,
        "fueltype": "Бензин",
        "transmission": 2
    },
    {
        "year": 7,
        "price": 16200,
        "oddmeter": 89000,
        "engine_V": 2.49,
        "fueltype": "Бензин",
        "transmission": 2
    },
    {
        "year": 0,
        "price": 31257,
        "oddmeter": 0,
        "engine_V": 2.5,
        "fueltype": "Бензин",
        "transmission": 2
    },
    {
        "year": 4,
        "price": 31500,
        "oddmeter": 22000,
        "engine_V": 2.49,
        "fueltype": "Бензин",
        "transmission": 2
    },
    {
        "year": 5,
        "price": 25300,
        "oddmeter": 101000,
        "engine_V": 2.5,
        "fueltype": "Бензин",
        "transmission": 2
    },
    {
        "year": 0,
        "price": 32194,
        "oddmeter": 0,
        "engine_V": 2.5,
        "fueltype": "Бензин",
        "transmission": 2
    },
    {
        "year": 0,
        "price": 32996,
        "oddmeter": 0,
        "engine_V": 2.5,
        "fueltype": "Бензин",
        "transmission": 2
    },
    {
        "year": 17,
        "price": 9900,
        "oddmeter": 257000,
        "engine_V": 3.5,
        "fueltype": "Бензин",
        "transmission": 2
    },
    {
        "year": 6,
        "price": 20900,
        "oddmeter": 63000,
        "engine_V": 2.49,
        "fueltype": "Бензин",
        "transmission": 2
    },
    {
        "year": 2,
        "price": 36900,
        "oddmeter": 52000,
        "engine_V": 2.5,
        "fueltype": "Гібрид",
        "transmission": 2
    },
    {
        "year": 2,
        "price": 32500,
        "oddmeter": 42000,
        "engine_V": 2.49,
        "fueltype": "Бензин",
        "transmission": 2
    },
    {
        "year": 4,
        "price": 27700,
        "oddmeter": 32000,
        "engine_V": 2.49,
        "fueltype": "Бензин",
        "transmission": 2
    },
    {
        "year": 5,
        "price": 27500,
        "oddmeter": 85000,
        "fueltype": "Газ/Бензин",
        "engine_V": 2.49,
        "transmission": 2
    },
    {
        "year": 19,
        "price": 5900,
        "oddmeter": 340000,
        "engine_V": 3.0,
        "fueltype": "Бензин",
        "transmission": 2
    },
    {
        "year": 13,
        "price": 12900,
        "oddmeter": 183000,
        "engine_V": 3.5,
        "fueltype": "Бензин",
        "transmission": 2
    },
    {
        "year": 15,
        "price": 8600,
        "oddmeter": 250000,
        "fueltype": "Газ/Бензин",
        "engine_V": 2.36,
        "transmission": 2
    },
    {
        "year": 2,
        "price": 36500,
        "oddmeter": 59000,
        "engine_V": 2.5,
        "fueltype": "Гібрид",
        "transmission": 4
    },
    {
        "year": 16,
        "price": 7790,
        "oddmeter": 260000,
        "fueltype": "Газ/Бензин",
        "engine_V": 2.4,
        "transmission": 2
    },
    {
        "year": 10,
        "price": 13500,
        "oddmeter": 183000,
        "engine_V": 2.49,
        "fueltype": "Гібрид",
        "transmission": 2
    },
    {
        "year": 6,
        "price": 25888,
        "oddmeter": 124000,
        "engine_V": 2.49,
        "fueltype": "Гібрид",
        "transmission": 2
    },
    {
        "year": 8,
        "price": 9999,
        "oddmeter": 180000,
        "engine_V": 2.5,
        "fueltype": "Бензин",
        "transmission": 2
    },
    {
        "year": 1,
        "price": 43000,
        "oddmeter": 5000,
        "engine_V": 2.49,
        "fueltype": "Гібрид",
        "transmission": 2
    },
    {
        "year": 10,
        "price": 14999,
        "oddmeter": 190000,
        "fueltype": "Газ/Бензин",
        "engine_V": 2.5,
        "transmission": 2
    },
    {
        "year": 16,
        "price": 9700,
        "oddmeter": 250000,
        "fueltype": "Газ/Бензин",
        "engine_V": 3.5,
        "transmission": 2
    },
    {
        "year": 10,
        "price": 13700,
        "oddmeter": 182000,
        "fueltype": "Газ/Бензин",
        "engine_V": 2.5,
        "transmission": 2
    }
]